pytboss/__init__.py
pytboss/_version.py
pytboss/api.py
pytboss/auth.py
pytboss/ble.py
pytboss/codec.py
pytboss/config.py
pytboss/exceptions.py
pytboss/fs.py
pytboss/grills.json
pytboss/grills.py
pytboss/py.typed
pytboss/transport.py
pytboss/wss.py
pytboss-2025.12.0.dist-info/licenses/LICENSE
pytboss-2025.12.0.dist-info/METADATA
pytboss-2025.12.0.dist-info/WHEEL
pytboss-2025.12.0.dist-info/top_level.txt
pytboss-2025.12.0.dist-info/zip-safe
pytboss-2025.12.0.dist-info/RECORD
