Metadata-Version: 2.4
Name: pytboss
Version: 2025.12.0
Summary: Python library for interacting with PitBoss grills and smokers.
Author-email: David Knowles <dknowles2@gmail.com>
License: Apache License 2.0
Project-URL: Homepage, https://github.com/dknowles2/pytboss
Project-URL: Source Code, https://github.com/dknowles2/pytboss
Project-URL: Bug Reports, https://github.com/dknowles2/pytboss/issues
Keywords: pitboss,api,iot,ble
Platform: any
Classifier: Programming Language :: Python :: 3.12
Classifier: Topic :: Software Development :: Libraries :: Python Modules
Requires-Python: >=3.12
License-File: LICENSE
Requires-Dist: aiohttp
Requires-Dist: bleak
Requires-Dist: bleak_retry_connector
Requires-Dist: dukpy
Requires-Dist: mypy_extensions
Dynamic: license-file
